pg_force_execute.py
pg_force_execute-0.0.11.dist-info/METADATA
pg_force_execute-0.0.11.dist-info/WHEEL
pg_force_execute-0.0.11.dist-info/licenses/LICENSE
pg_force_execute-0.0.11.dist-info/RECORD
