Metadata-Version: 2.1
Name: pg-force-execute
Version: 0.0.11
Summary: Context manager to run PostgreSQL queries with SQLAlchemy, terminating any other clients that block them
Project-URL: Source, https://github.com/uktrade/pg-force-execute
Author-email: Department for International Trade <sre@digital.trade.gov.uk>
License-File: LICENSE
Classifier: License :: OSI Approved :: MIT License
Classifier: Operating System :: OS Independent
Classifier: Programming Language :: Python :: 3
Requires-Python: >=3.7.1
Requires-Dist: sqlalchemy>=1.4.24
Provides-Extra: ci
Requires-Dist: pytest==7.2.1; extra == 'ci'
Provides-Extra: ci-psycopg2-sqlalchemy1
Requires-Dist: psycopg2==2.9.2; extra == 'ci-psycopg2-sqlalchemy1'
Requires-Dist: sqlalchemy==1.4.24; extra == 'ci-psycopg2-sqlalchemy1'
Provides-Extra: ci-psycopg2-sqlalchemy2
Requires-Dist: psycopg2==2.9.2; extra == 'ci-psycopg2-sqlalchemy2'
Requires-Dist: sqlalchemy==2.0.0; extra == 'ci-psycopg2-sqlalchemy2'
Provides-Extra: ci-psycopg3-sqlalchemy2
Requires-Dist: psycopg==3.1.4; extra == 'ci-psycopg3-sqlalchemy2'
Requires-Dist: sqlalchemy==2.0.0; extra == 'ci-psycopg3-sqlalchemy2'
Provides-Extra: dev
Requires-Dist: psycopg2>=2.9.2; extra == 'dev'
Requires-Dist: psycopg>=3.1.4; extra == 'dev'
Requires-Dist: pytest>=7.2.1; extra == 'dev'
